Workbook

Sheet EXECUTIVE SUMMARY
A1: AI Revenue Recovery OS — Product Build & Investment Model
A2: Provider + Payer platform · Azure · AI workforce · August 18, 2026
A3: MODEL ASSUMPTIONS with sourced 2026 pricing. Not HIPAA-certified — HIPAA-aligned architecture + program. Quote-only prices marked 'Not publicly disclosed'. No PHI.
A5: Headline | B5: USD | C5: INR
A6: Total MVP investment (est.) | B6: 383068 | C6: =B6*'ASSUMPTIONS'!$B$6
A7: 12-month investment (est.) | B7: 1492847 | C7: =B7*'ASSUMPTIONS'!$B$6
A8: 24-month investment (est.) | B8: 4450298 | C8: =B8*'ASSUMPTIONS'!$B$6
A9: Avg monthly burn — year 1 | B9: 124404 | C9: =B9*'ASSUMPTIONS'!$B$6
A10: Azure — MVP / month | B10: 1377 | C10: =B10*'ASSUMPTIONS'!$B$6
A11: Azure — Medium production / month | B11: 7176 | C11: =B11*'ASSUMPTIONS'!$B$6
A12: Claude Max baseline / month (5 × 20x) | B12: 1000 | C12: =B12*'ASSUMPTIONS'!$B$6
A13: ChatGPT baseline / month (5 users) | B13: 100 | C13: =B13*'ASSUMPTIONS'!$B$6
A14: Production AI runtime — Medium / month | B14: 96350 | C14: =B14*'ASSUMPTIONS'!$B$6
A15: All-in cost per worked claim | B15: 0.4322 | C15: =B15*'ASSUMPTIONS'!$B$6
A17: Recommendation: build the common platform from day one; launch Provider/RCM first; add Payer (decision-support) after validation. Baseline team 5 FTE × Claude Max 20x; Azure Container Apps + PostgreSQL Flexible Server + private networking at production; HIPAA-aligned with SOC 2 on the roadmap.

Sheet ASSUMPTIONS
A1: Assumptions (edit these — dependent sheets recalculate)
A2: Yellow cells are inputs.
A3: MODEL ASSUMPTIONS. Prices are researched 2026 figures (see SOURCES). Quote-only items are 'Not publicly disclosed' and never invented.
A6: USD to INR exchange rate | B6: 90
A7: Contingency % | B7: 0.15
A8: Claims / month (MVP) | B8: 50000
A9: Claims / month (Medium) | B9: 500000
A10: Claims / month (Large) | B10: 5000000
A11: AI cost per claim (USD) | B11: 0.1211
A12: Voice cost per claim (USD) | B12: 0.0576
A13: Document AI per claim (USD) | B13: 0.0135
A14: Clearinghouse per claim (USD) | B14: 0.24
A15: Claude Max 20x ($/user/mo) | B15: 200
A16: Claude Max users (baseline) | B16: 5
A17: ChatGPT Business ($/user/mo) | B17: 20
... A19: Team fully-loaded factor | B19: 1.4
A21: Yellow = input; green = calculated. Changing an input recalculates dependent sheets on open.

Sheet THREE PRODUCT MODELS
A1: Three product models
A3: Model | B3: Customer | C3: Positioning | D3: Regulatory posture
A4: A — Provider / RCM | B4: Billing/RCM cos, hospitals, health systems, groups | C4: Provider revenue automation across the RCM lifecycle | D4: BAA; standard SaaS
A5: B — Payer | B5: Insurers, health plans, MA orgs, Medicaid MCOs, TPAs | C5: AI decision-support + workflow automation with payer governance | D5: Model A/B; delegated funcs need legal review
A6: C — Provider + Payer | B6: Long-term platform | C6: Shared foundation with strict tenant isolation | D6: Never mix tenant data; authorized cross-party only

Sheet PROVIDER ARCHITECTURE
A1: Provider architecture
A3: Layer / Component | B3: Description
A4: Ingress | B4: Front Door → WAF → APIM → Entra ID
A5: Provider API | B5: Eligibility, benefits, estimation, prior auth, claims, status, denials, appeals, recovery
A6: Orchestration | B6: Right-channel engine: EDI → API → FHIR → Portal → Voice → Human
A7: Data | B7: PostgreSQL (RLS by tenant), Blob (claims/docs), Redis
A8: AI | B8: AI Gateway + RAG (payer policies), denial/appeal intelligence
A9: Connectivity | B9: Clearinghouse APIs (Stedi/Optum/Availity), payer FHIR (2027)

Sheet PAYER ARCHITECTURE
A1: Payer architecture (decision-support)
A3: Layer / Component | B3: Description
A4: Ingress | B4: Same secured ingress; payer tenant isolation
A5: Payer API | B5: Claim intake, validation, adjudication decision-support, payment integrity, denial ops, appeals, provider comms
A6: Governance | B6: AI recommendation → rules validation → human/payer approval → execution → audit
A7: Guardrail | B7: No final coverage/medical-necessity/payment decision by AI alone (CMS-4201-F; SB 1120)
A8: Data | B8: Payer tenant DB / dedicated for enterprise; never visible to provider tenants
A9: Intelligence | B9: Payer Intelligence + coverage-policy RAG (NCD/LCD; license InterQual/MCG)

Sheet COMBINED ARCHITECTURE
A1: Combined (provider + payer) architecture
A3: Layer / Component | B3: Description
A4: Tenancy | B4: PLATFORM · PROVIDER · PAYER · RCM/BPO · ENTERPRISE; every record tenant_id/org_id/env_id
A5: Isolation | B5: App + DB RLS (MVP) → schema/keys (V1) → dedicated DB/env (Enterprise)
A6: Cross-party | B6: Authorized, purpose-limited, logged, encrypted, tenant-aware, contractual only
A7: Shared core | B7: Orchestration, Payer Intelligence, audit, security — built once
A8: Separation | B8: Provider data never auto-visible to payer, and vice versa

Sheet TECHNOLOGY STACK
A1: Technology stack
A3: Layer | B3: Technology
A4: Cloud | B4: Microsoft Azure (East US 2 primary)
A5: Compute | B5: Azure Container Apps (AKS only when justified)
A6: Data | B6: PostgreSQL Flexible Server (RLS, HA, PITR)
A7: Cache | B7: Azure Cache for Redis / Managed Redis
A8: Messaging | B8: Azure Service Bus
A9: Storage | B9: Azure Blob (private, encrypted, lifecycle)
A10: Search/RAG | B10: Azure AI Search (vector)
A11: Identity | B11: Microsoft Entra ID (MFA, CA, PIM, Managed Identity)
A12: API | B12: Azure API Management + Front Door + WAF
A13: AI | B13: AI Gateway → Azure OpenAI (PHI/BAA) · Anthropic · OpenAI
A14: Security | B14: Key Vault/HSM, Private Link, Firewall, Defender, Sentinel, Monitor
A15: CI/CD | B15: GitHub + Actions; SAST/DAST/SCA/secret/container/IaC scanning

Sheet AZURE ARCHITECTURE
A1: Azure architecture — tiers
A2: Do not over-engineer the MVP; add premium networking/security at production.
A4: Tier | B4: Footprint
A5: MVP | B5: Container Apps · PostgreSQL Flex · Blob · Service Bus · Key Vault · Entra ID · App Insights · Monitor · WAF · (APIM)
A6: Production | B6: + HA · Private endpoints · Azure Firewall · Defender · Sentinel · advanced monitoring · DR · geo-redundancy · HSM (where justified)
A7: Large enterprise | B7: + Dedicated env/DB/keys/networking/logging · optional regional deployment

Sheet AZURE COST
A1: Azure cost — MVP line items (USD + INR)
A2: INR = USD × exchange rate (ASSUMPTIONS). Monthly figures are MODEL ASSUMPTIONS derived from unit rates.
A4: Service | B4: Tier | C4: Monthly USD | D4: Monthly INR | E4: Annual USD | F4: Source
A5: Container Apps | B5: Consumption (scaled) | C5: 120 | D5: =C5*'ASSUMPTIONS'!$B$6 | E5: =C5*12 | F5: https://azure.microsoft.com/en-us/pricing/details/container-apps/
A6: PostgreSQL Flexible Server | B6: GP D4ds_v5 + HA | C6: 500 | D6: =C6*'ASSUMPTIONS'!$B$6 | E6: =C6*12 | F6: https://azure.microsoft.com/en-us/pricing/details/postgresql/flexible-server/
A7: Cache for Redis | B7: Standard C1 | C7: 52 | D7: =C7*'ASSUMPTIONS'!$B$6 | E7: =C7*12 | F7: https://azure.microsoft.com/en-us/pricing/details/cache/
A8: Blob Storage | B8: Hot LRS | C8: 40 | D8: =C8*'ASSUMPTIONS'!$B$6 | E8: =C8*12 | F8: https://azure.microsoft.com/en-us/pricing/details/storage/blobs/
A9: Service Bus | B9: Standard | C9: 30 | D9: =C9*'ASSUMPTIONS'!$B$6 | E9: =C9*12 | F9: https://azure.microsoft.com/en-us/pricing/details/service-bus/
A10: Key Vault | B10: Standard | C10: 15 | D10: =C10*'ASSUMPTIONS'!$B$6 | E10: =C10*12 | F10: https://azure.microsoft.com/en-us/pricing/details/key-vault/
A11: Front Door | B11: Standard + custom WAF | C11: 35 | D11: =C11*'ASSUMPTIONS'!$B$6 | E11: =C11*12 | F11: https://azure.microsoft.com/en-us/pricing/details/frontdoor/
A12: API Management | B12: Basic v2 | C12: 210 | D12: =C12*'ASSUMPTIONS'!$B$6 | E12: =C12*12 | F12: https://azure.microsoft.com/en-us/pricing/details/api-management/
A13: Defender for Cloud | B13: Servers P2 (few) | C13: 60 | D13: =C13*'ASSUMPTIONS'!$B$6 | E13: =C13*12 | F13: https://azure.microsoft.com/en-us/pricing/details/defender-for-cloud/
A14: Sentinel + Log Analytics | B14: ~30 GB/mo | C14: 150 | D14: =C14*'ASSUMPTIONS'!$B$6 | E14: =C14*12 | F14: https://azure.microsoft.com/en-us/pricing/details/microsoft-sentinel/
A15: Azure Monitor / App Insights | B15: PAYG | C15: 40 | D15: =C15*'ASSUMPTIONS'!$B$6 | E15: =C15*12 | F15: https://azure.microsoft.com/en-us/pricing/details/monitor/
A16: Container Registry | B16: Standard | C16: 20 | D16: =C16*'ASSUMPTIONS'!$B$6 | E16: =C16*12 | F16: https://azure.microsoft.com/en-us/pricing/details/container-registry/
... A18: Azure AI Search | B18: Basic | C18: 75 | D18: =C18*'ASSUMPTIONS'!$B$6 | E18: =C18*12 | F18: https://azure.microsoft.com/en-us/pricing/details/search/
A19: TOTAL (MVP / month) | C19: =SUM(C5:C18) | D19: =C19*'ASSUMPTIONS'!$B$6

Sheet AZURE COST BY ENVIRONMENT
A1: Azure cost by environment (share of production)
A3: Environment | B3: Sizing vs prod | C3: Monthly USD (est.) | D3: Monthly INR
A4: DEV | B4: 10% | C4: 718 | D4: =C4*'ASSUMPTIONS'!$B$6
A5: TEST | B5: 10% | C5: 718 | D5: =C5*'ASSUMPTIONS'!$B$6
A6: STAGING | B6: 25% | C6: 1794 | D6: =C6*'ASSUMPTIONS'!$B$6
A7: PRODUCTION | B7: 100% | C7: 7176 | D7: =C7*'ASSUMPTIONS'!$B$6

Sheet AZURE COST BY SCALE
A1: Azure monthly cost by scale (all line items)
A2: Per-service monthly MODEL ASSUMPTIONS from unit rates; INR via exchange rate.
A4: Scenario | B4: Service | C4: Tier | D4: Monthly USD | E4: Monthly INR
A5: Development | B5: Container Apps | C5: Consumption | D5: 40 | E5: =D5*'ASSUMPTIONS'!$B$6
A6: Development | B6: PostgreSQL Flexible Server | C6: GP D2ds_v5 (no HA) | D6: 200 | E6: =D6*'ASSUMPTIONS'!$B$6
A7: Development | B7: Blob Storage | C7: Hot LRS | D7: 10 | E7: =D7*'ASSUMPTIONS'!$B$6
A8: Development | B8: Service Bus | C8: Standard | D8: 10 | E8: =D8*'ASSUMPTIONS'!$B$6
A9: Development | B9: Cache for Redis | C9: Basic C0 | D9: 12 | E9: =D9*'ASSUMPTIONS'!$B$6
A10: Development | B10: Key Vault | C10: Standard | D10: 5 | E10: =D10*'ASSUMPTIONS'!$B$6
A11: Development | B11: Front Door | C11: Standard | D11: 35 | E11: =D11*'ASSUMPTIONS'!$B$6
A12: Development | B12: API Management | C12: Developer | D12: 48 | E12: =D12*'ASSUMPTIONS'!$B$6
A13: Development | B13: Log Analytics / Monitor | C13: PAYG (~5GB) | D13: 20 | E13: =D13*'ASSUMPTIONS'!$B$6
A14: Development | B14: Container Registry | C14: Basic | D14: 5 | E14: =D14*'ASSUMPTIONS'!$B$6
A15: MVP / Pilot | B15: Container Apps | C15: Consumption (scaled) | D15: 120 | E15: =D15*'ASSUMPTIONS'!$B$6
A16: MVP / Pilot | B16: PostgreSQL Flexible Server | C16: GP D4ds_v5 + HA | D16: 500 | E16: =D16*'ASSUMPTIONS'!$B$6
... A61: Large Production | B61: DDoS Network Protection | C61: Standard | D61: 2944 | E61: =D61*'ASSUMPTIONS'!$B$6

Sheet CLAUDE MAX COST
A1: Claude Max cost
A2: Baseline: 5 users × Max 20x. NOT one subscription per AI agent.
A3: Claude Code is included in Max (no separate subscription). Production API tokens are billed separately (see PRODUCTION AI COST).
A5: Users | B5: Plan | C5: $/user/mo | D5: Monthly USD | E5: Annual USD | F5: 12-mo USD | G5: 24-mo USD
A6: 3 | B6: Max 5x | C6: 100 | D6: =A6*C6 | E6: =D6*12 | F6: =D6*12 | G6: =D6*24
A7: 3 | B7: Max 20x | C7: 200 | D7: =A7*C7 | E7: =D7*12 | F7: =D7*12 | G7: =D7*24
A8: 5 | B8: Max 5x | C8: 100 | D8: =A8*C8 | E8: =D8*12 | F8: =D8*12 | G8: =D8*24
A9: 5 | B9: Max 20x | C9: 200 | D9: =A9*C9 | E9: =D9*12 | F9: =D9*12 | G9: =D9*24
A10: 10 | B10: Max 5x | C10: 100 | D10: =A10*C10 | E10: =D10*12 | F10: =D10*12 | G10: =D10*24
A11: 10 | B11: Max 20x | C11: 200 | D11: =A11*C11 | E11: =D11*12 | F11: =D11*12 | G11: =D11*24
A12: 15 | B12: Max 5x | C12: 100 | D12: =A12*C12 | E12: =D12*12 | F12: =D12*12 | G12: =D12*24
A13: 15 | B13: Max 20x | C13: 200 | D13: =A13*C13 | E13: =D13*12 | F13: =D13*12 | G13: =D13*24
A15: Baseline (from ASSUMPTIONS) | D15: ='ASSUMPTIONS'!$B$16*'ASSUMPTIONS'!$B$15

Sheet CHATGPT COST
A1: ChatGPT cost
A2: ChatGPT Business (formerly Team). Enterprise is quote-only.
A3: A ChatGPT subscription is NOT production API credits (see PRODUCTION AI COST).
A5: Users | B5: Plan | C5: $/user/mo | D5: Monthly USD | E5: Annual USD | F5: 12-mo USD | G5: 24-mo USD
A6: 5 | B6: Business Standard | C6: 20 | D6: =A6*C6 | E6: =D6*12 | F6: =D6*12 | G6: =D6*24
A7: 10 | B7: Business Standard | C7: 20 | D7: =A7*C7 | E7: =D7*12 | F7: =D7*12 | G7: =D7*24
A8: 15 | B8: Business Standard | C8: 20 | D8: =A8*C8 | E8: =D8*12 | F8: =D8*12 | G8: =D8*24
A9: 20 | B9: Business Standard | C9: 20 | D9: =A9*C9 | E9: =D9*12 | F9: =D9*12 | G9: =D9*24
A11: ChatGPT Enterprise | B11: Not publicly disclosed (quote-only)

Sheet PRODUCTION AI COST
A1: Production AI runtime cost
A2: Per-token / per-minute usage — separate from dev-tool subscriptions.
A3: AI API token prices are 2026 MODEL ASSUMPTIONS (verify live). Azure OpenAI is the PHI path (covered by Microsoft BAA).
A5: Scenario | B5: Claims/mo | C5: AI/claim | D5: Voice/claim | E5: Doc/claim | F5: AI+Voice+Doc /mo USD | G5: AI Search /mo | H5: Total /mo USD | I5: Total /mo INR
A6: MVP / Pilot | B6: ='ASSUMPTIONS'!$B$8 | C6: ='ASSUMPTIONS'!$B$11 | D6: ='ASSUMPTIONS'!$B$12 | E6: ='ASSUMPTIONS'!$B$13 | F6: =B6*(C6+D6+E6) | G6: 75 | H6: =F6+G6 | I6: =H6*'ASSUMPTIONS'!$B$6
A7: Medium Production | B7: ='ASSUMPTIONS'!$B$9 | C7: ='ASSUMPTIONS'!$B$11 | D7: ='ASSUMPTIONS'!$B$12 | E7: ='ASSUMPTIONS'!$B$13 | F7: =B7*(C7+D7+E7) | G7: 250 | H7: =F7+G7 | I7: =H7*'ASSUMPTIONS'!$B$6
A8: Large Production | B8: ='ASSUMPTIONS'!$B$10 | C8: ='ASSUMPTIONS'!$B$11 | D8: ='ASSUMPTIONS'!$B$12 | E8: ='ASSUMPTIONS'!$B$13 | F8: =B8*(C8+D8+E8) | G8: 1000 | H8: =F8+G8 | I8: =H8*'ASSUMPTIONS'!$B$6
A10: AI token prices ($/1M) — MODEL ASSUMPTION
A11: Model | B11: Input | C11: Output
A12: Claude Haiku 4.5 | B12: 1 | C12: 5
A13: Claude Sonnet 4.6 | B13: 3 | C13: 15
A14: Claude Opus 4.8 | B14: 5 | C14: 25
A15: Azure OpenAI GPT-4o (PHI/BAA path) | B15: 2.5 | C15: 10
A16: OpenAI text-embedding-3-small | B16: 0.02 | C16: 0

Sheet AI AGENT WORKFORCE
A1: AI agent workforce (20 agents)
A2: Operated by humans via AI tools — NOT one subscription per agent.
A4: # | B4: AI Agent | C4: Governance
A5: 1 | B5: Product Manager | C5: Scoped tool/data/tenant/action permissions + audit; high-risk actions human-approved
A6: 2 | B6: Project Manager | C6: Scoped tool/data/tenant/action permissions + audit; high-risk actions human-approved
A7: 3 | B7: Business Analyst | C7: Scoped tool/data/tenant/action permissions + audit; high-risk actions human-approved
A8: 4 | B8: Healthcare RCM | C8: Scoped tool/data/tenant/action permissions + audit; high-risk actions human-approved
A9: 5 | B9: Payer Research | C9: Scoped tool/data/tenant/action permissions + audit; high-risk actions human-approved
A10: 6 | B10: Architecture | C10: Scoped tool/data/tenant/action permissions + audit; high-risk actions human-approved
A11: 7 | B11: Backend Developer | C11: Scoped tool/data/tenant/action permissions + audit; high-risk actions human-approved
A12: 8 | B12: Frontend Developer | C12: Scoped tool/data/tenant/action permissions + audit; high-risk actions human-approved
A13: 9 | B13: AI Engineer | C13: Scoped tool/data/tenant/action permissions + audit; high-risk actions human-approved
A14: 10 | B14: EDI | C14: Scoped tool/data/tenant/action permissions + audit; high-risk actions human-approved
A15: 11 | B15: FHIR | C15: Scoped tool/data/tenant/action permissions + audit; high-risk actions human-approved
A16: 12 | B16: Integration | C16: Scoped tool/data/tenant/action permissions + audit; high-risk actions human-approved
... A24: 20 | B24: Test Data | C24: Scoped tool/data/tenant/action permissions + audit; high-risk actions human-approved

Sheet HUMAN RESOURCES
A1: Human resources — India salary bands (annual base USD)
A2: Loaded cost = base × factor (ASSUMPTIONS). Ranges, not quotes. Sources: Glassdoor/6figr/Levels.
A4: Role | B4: Low USD | C4: Mid USD | D4: High USD | E4: Loaded Mid USD | F4: Loaded Mid INR
A5: CTO / Principal Architect | B5: 46000 | C5: 86000 | D5: 172000 | E5: =C5*'ASSUMPTIONS'!$B$19 | F5: =E5*'ASSUMPTIONS'!$B$6
A6: Product Manager | B6: 23000 | C6: 40000 | D6: 63000 | E6: =C6*'ASSUMPTIONS'!$B$19 | F6: =E6*'ASSUMPTIONS'!$B$6
A7: Healthcare / RCM Business Analyst | B7: 7000 | C7: 14000 | D7: 23000 | E7: =C7*'ASSUMPTIONS'!$B$19 | F7: =E7*'ASSUMPTIONS'!$B$6
A8: Senior Backend Engineer | B8: 21000 | C8: 34000 | D8: 57000 | E8: =C8*'ASSUMPTIONS'!$B$19 | F8: =E8*'ASSUMPTIONS'!$B$6
A9: Senior Frontend Engineer | B9: 17000 | C9: 30000 | D9: 52000 | E9: =C9*'ASSUMPTIONS'!$B$19 | F9: =E9*'ASSUMPTIONS'!$B$6
A10: AI / ML Engineer | B10: 23000 | C10: 40000 | D10: 69000 | E10: =C10*'ASSUMPTIONS'!$B$19 | F10: =E10*'ASSUMPTIONS'!$B$6
A11: Integration Engineer (EDI/FHIR) | B11: 14000 | C11: 25000 | D11: 44000 | E11: =C11*'ASSUMPTIONS'!$B$19 | F11: =E11*'ASSUMPTIONS'!$B$6
A12: DevOps / SRE Engineer | B12: 21000 | C12: 32000 | D12: 57000 | E12: =C12*'ASSUMPTIONS'!$B$19 | F12: =E12*'ASSUMPTIONS'!$B$6
A13: Security Engineer | B13: 17000 | C13: 32000 | D13: 52000 | E13: =C13*'ASSUMPTIONS'!$B$19 | F13: =E13*'ASSUMPTIONS'!$B$6
A14: QA Engineer | B14: 9000 | C14: 17000 | D14: 29000 | E14: =C14*'ASSUMPTIONS'!$B$19 | F14: =E14*'ASSUMPTIONS'!$B$6
A15: Data Engineer | B15: 14000 | C15: 28000 | D15: 48000 | E15: =C15*'ASSUMPTIONS'!$B$19 | F15: =E15*'ASSUMPTIONS'!$B$6
A16: Compliance Consultant (fractional) | B16: 18000 | C16: 36000 | D16: 60000 | E16: =C16*'ASSUMPTIONS'!$B$19 | F16: =E16*'ASSUMPTIONS'!$B$6

Sheet DEVELOPMENT COST
A1: Development cost by team model (annual, loaded)
A3: Team model | B3: Roles | C3: Low USD | D3: Mid USD | E3: High USD
A4: Lean MVP (5) | B4: 5 | C4: 179200 | D4: 310800 | E4: 569800
A5: Balanced MVP (8) | B5: 8 | C5: 235200 | D5: 414400 | E5: 744800
A6: Production (13) | B6: 13 | C6: 345800 | D6: 624400 | E6: 1089200
A8: MVP build (Lean team × 8 mo) | D8: 207200
A9: To production (Balanced × 11.5 mo) | D9: 397133

Sheet SECURITY COST
A1: Security & compliance cost
A2: Ranges from benchmarks (Secureframe/Drata/Bright Defense). Not quotes.
A4: Item | B4: One-time Low | C4: One-time High | D4: Annual Low | E4: Annual High | F4: Category
A5: HIPAA risk / gap assessment | B5: 5000 | C5: 20000 | F5: one-time
A6: HIPAA policies / SOPs + training | B6: 4000 | C6: 12000 | F6: one-time
A7: Compliance automation tooling (Vanta/Drata) | D7: 7500 | E7: 50000 | F7: annual
A8: Penetration test (web + API) | B8: 8000 | C8: 25000 | F8: per engagement
A9: vCISO / fractional CISO | D9: 30000 | E9: 180000 | F9: annual
A10: SIEM / managed SOC (MDR) | D10: 6000 | E10: 60000 | F10: annual
A11: SOC 2 Type I | B11: 15000 | C11: 35000 | F11: one-time
A12: SOC 2 Type II (all-in first year) | B12: 30000 | C12: 80000 | F12: one-time
A13: HITRUST i1 (roadmap) | B13: 60000 | C13: 200000 | F13: one-time (later)
A14: Security training (per employee/yr) | D14: 85 | E14: 150 | F14: annual/employee

Sheet HIPAA _ PHI COST
A1: HIPAA / PHI program cost
A2: HIPAA is a program, not a certification. Azure BAA is included (Product Terms/DPA).
A4: Item | B4: Low USD | C4: High USD | D4: Note
A5: HIPAA gap/risk assessment | B5: 5000 | C5: 20000 | D5: HHS SRA tool (DIY) → external engagement
A6: Policies / SOPs + training | B6: 4000 | C6: 12000 | D6: Training ~$85/employee/yr
A7: Technical safeguards (in Azure cost) | D7: Encryption, Key Vault, private networking, audit
A8: Security testing / pen test | B8: 8000 | C8: 25000 | D8: Web + API
A9: Azure HIPAA BAA | B9: 0 | C9: 0 | D9: Included via Microsoft Product Terms/DPA
A10: Incident response readiness | B10: 5000 | C10: 20000 | D10: Runbooks + retainer

Sheet COMPLIANCE
A1: Compliance roadmap (SOC 2 / HITRUST)
A2: Do not claim certification before achieved.
A4: Framework | B4: Timing | C4: Cost range | D4: Effort | E4: Business value
A5: SOC 2 Type I | B5: M10–M11 | C5: $15k–35k | D5: Readiness + point-in-time audit | E5: Provider trust; sales enabler
A6: SOC 2 Type II | B6: M12 + 6-mo window | C6: $30k–80k | D6: 6-month observation + audit | E6: Enterprise/payer requirement
A7: HITRUST i1 | B7: Year 2 | C7: $60k–200k | D7: If a payer/enterprise customer demands it | E7: Payer contracts; high assurance
A8: HIPAA program | B8: M10 ongoing | C8: $20k–40k + tooling | D8: Risk assessment, policies, training, evidence | E8: Table stakes for PHI

Sheet MILESTONES
A1: Milestones M0–M12 (realistic weeks)
A3: # | B3: Milestone | C3: Weeks | D3: Depends on | E3: Key deliverables
A4: M0 | B4: Discovery | C4: 2 | D4: — | E4: Requirements, payer/API/security research
A5: M1 | B5: Architecture + Security foundation | C5: 3 | D5: M0 | E5: Azure, Entra, networking, tenant model, CI/CD
A6: M2 | B6: Multi-tenant core | C6: 4 | D6: M1 | E6: Tenants, RBAC, orgs, users, audit, admin
A7: M3 | B7: Eligibility + Benefits | C7: 4 | D7: M2 | E7: 270/271, integration framework, payer config
A8: M4 | B8: Claim Status | C8: 3 | D8: M3 | E8: 276/277, timeline, status agent
A9: M5 | B9: Prior Authorization | C9: 4 | D9: M3 | E9: 278/FHIR, PA workflow, document workflow
A10: M6 | B10: Denial Intelligence | C10: 4 | D10: M4 | E10: 835/CARC/RARC, analysis, recovery
A11: M7 | B11: Appeals | C11: 3 | D11: M6 | E11: Draft, human approval, tracking
A12: M8 | B12: Payer Intelligence | C12: 4 | D12: M3-M7 | E12: Payer DB, RAG, recommendation engine
A13: M9 | B13: AI Workforce | C13: 3 | D13: M8 | E13: Agent orchestration, registry, audit
A14: M10 | B14: Security / HIPAA hardening | C14: 4 | D14: M1-M9 | E14: Risk assessment, pen test, PHI controls
A15: M11 | B15: Pilot | C15: 4 | D15: M10 | E15: Design partner, approved data, metrics
A16: M12 | B16: Production readiness | C16: 4 | D16: M11 | E16: HA, DR, monitoring, runbooks, release
A18: Aggressive ≈ 0.8× · Realistic = 1.0× (~46 wk) · Conservative ≈ 1.3×

Sheet PROJECT PLAN
A1: Project plan summary
A3: Area | B3: Approach
A4: PM platform | B4: GitHub Projects (recommended) → Linear/Jira as team scales
A5: Workflow | B5: Requirement → AI PM → story → AI architect → AI dev → AI QA/Security → PR → human review → CI/CD → staging → human approval → prod
A6: Git | B6: main (protected), develop, feature/*, bugfix/*, security/*; mandatory PR + scans
A7: Team | B7: Lean 5 → Balanced 8 → Production 12–15; 5 × Claude Max 20x baseline
A8: AI productivity | B8: +10/20/30/40% scenarios; plan on +30%
A9: Timeline | B9: MVP ~M8–M9 (~32 wk), pilot ~M11 (~40 wk), production ~M12 (~46 wk) realistic

Sheet CLOUD COST
A1: Cloud + runtime cost summary by scenario (monthly USD)
A3: Scenario | B3: Azure | C3: AI runtime | D3: Clearinghouse | E3: Total /mo | F3: Total /mo INR
A4: Development | B4: 385 | C4: 459.4 | D4: 480 | E4: =B4+C4+D4 | F4: =E4*'ASSUMPTIONS'!$B$6
A5: MVP / Pilot | B5: 1377 | C5: 9685 | D5: 12000 | E5: =B5+C5+D5 | F5: =E5*'ASSUMPTIONS'!$B$6
A6: Medium Production | B6: 7176 | C6: 96350 | D6: 120000 | E6: =B6+C6+D6 | F6: =E6*'ASSUMPTIONS'!$B$6
A7: Large Production | B7: 38694 | C7: 962000 | D7: 1200000 | E7: =B7+C7+D7 | F7: =E7*'ASSUMPTIONS'!$B$6

Sheet UNIT ECONOMICS
A1: Unit economics (cost per action)
A2: AI + channel cost. Clearinghouse per transaction is a MODEL ASSUMPTION (Stedi free tier covers MVP).
A4: Action | B4: AI cost USD | C4: Channel cost USD | D4: Total USD | E4: Note
A5: Eligibility check | B5: 0.005 | C5: 0.12 | D5: =B5+C5 | E5: Haiku parse + 270/271 txn
A6: Benefit verification | B6: 0.006 | C6: 0.12 | D6: =B6+C6 | E6: 271 parse + txn
A7: Claim status | B7: 0.005 | C7: 0.12 | D7: =B7+C7 | E7: 276/277 txn
A8: Prior authorization | B8: 0.05 | C8: 0.12 | D8: =B8+C8 | E8: reasoning + 278/portal
A9: Denial analysis | B9: 0.1 | C9: 0 | D9: =B9+C9 | E9: Opus root-cause (835 already received)
A10: Appeal draft | B10: 0.15 | C10: 0 | D10: =B10+C10 | E10: Opus draft + human review
A11: AI agent action (generic) | B11: 0.02 | C11: 0 | D11: =B11+C11 | E11: orchestration step
A13: All-in cost per worked claim (blended) | D13: 0.4322

Sheet MVP COST
A1: MVP investment (one-time, ~8 months)
A3: Line item | B3: USD | C3: INR
A4: Development (lean team) | B4: 207200 | C4: =B4*'ASSUMPTIONS'!$B$6
A5: Azure (build ramp) | B5: 7048 | C5: =B5*'ASSUMPTIONS'!$B$6
A6: AI dev subscriptions | B6: 8800 | C6: =B6*'ASSUMPTIONS'!$B$6
A7: AI API (pilot volume) | B7: 29055 | C7: =B7*'ASSUMPTIONS'!$B$6
A8: Security / HIPAA (one-time) | B8: 36000 | C8: =B8*'ASSUMPTIONS'!$B$6
A9: Clearinghouse setup | B9: 5000 | C9: =B9*'ASSUMPTIONS'!$B$6
A10: Legal (BAA/contracts) | B10: 25000 | C10: =B10*'ASSUMPTIONS'!$B$6
A11: Testing | B11: 15000 | C11: =B11*'ASSUMPTIONS'!$B$6
A12: Contingency (15%) | B12: 49965 | C12: =B12*'ASSUMPTIONS'!$B$6
A13: TOTAL | B13: =SUM(B4:B12) | C13: =B13*'ASSUMPTIONS'!$B$6

Sheet PILOT COST
A1: Pilot phase (incremental)
A3: Line item | B3: USD | C3: INR
A4: Design-partner enablement | B4: 20000 | C4: =B4*'ASSUMPTIONS'!$B$6
A5: Azure (MVP tier × 3 mo) | B5: 4131 | C5: =B5*'ASSUMPTIONS'!$B$6
A6: AI runtime (pilot × 3 mo) | B6: 29055 | C6: =B6*'ASSUMPTIONS'!$B$6
A7: Security monitoring | B7: 15000 | C7: =B7*'ASSUMPTIONS'!$B$6
A8: Support | B8: 10000 | C8: =B8*'ASSUMPTIONS'!$B$6
A9: TOTAL | B9: =SUM(B4:B8) | C9: =B9*'ASSUMPTIONS'!$B$6

Sheet PRODUCTION COST
A1: Production readiness (incremental)
A3: Line item | B3: USD | C3: INR
A4: Development to production | B4: 189933 | C4: =B4*'ASSUMPTIONS'!$B$6
A5: Azure (Medium × 6 mo) | B5: 43056 | C5: =B5*'ASSUMPTIONS'!$B$6
A6: AI runtime (Medium × 6 mo) | B6: 578100 | C6: =B6*'ASSUMPTIONS'!$B$6
A7: SOC 2 Type II | B7: 50000 | C7: =B7*'ASSUMPTIONS'!$B$6
A8: Pen test (annual) | B8: 18000 | C8: =B8*'ASSUMPTIONS'!$B$6
A9: DR + monitoring | B9: 20000 | C9: =B9*'ASSUMPTIONS'!$B$6
A10: TOTAL | B10: =SUM(B4:B9) | C10: =B10*'ASSUMPTIONS'!$B$6

Sheet 12 MONTH BUDGET
A1: 12-month budget
A3: Category | B3: USD | C3: INR
A4: Team (Balanced 8, loaded) | B4: 414400 | C4: =B4*'ASSUMPTIONS'!$B$6
A5: Azure (MVP→Medium) | B5: 51318 | C5: =B5*'ASSUMPTIONS'!$B$6
A6: AI runtime | B6: 636210 | C6: =B6*'ASSUMPTIONS'!$B$6
A7: AI dev subscriptions | B7: 13200 | C7: =B7*'ASSUMPTIONS'!$B$6
A8: Security + SOC2 Type I | B8: 138000 | C8: =B8*'ASSUMPTIONS'!$B$6
A9: Legal + testing + clearinghouse | B9: 45000 | C9: =B9*'ASSUMPTIONS'!$B$6
A10: TOTAL (incl. contingency) | B10: 1492847 | C10: =B10*'ASSUMPTIONS'!$B$6

Sheet 24 MONTH BUDGET
A1: 24-month budget
A3: Category | B3: USD | C3: INR
A4: Team (scale to production) | B4: 1038800 | C4: =B4*'ASSUMPTIONS'!$B$6
A5: Azure (Medium × 24 mo) | B5: 172224 | C5: =B5*'ASSUMPTIONS'!$B$6
A6: AI runtime (Medium × 24 mo) | B6: 2312400 | C6: =B6*'ASSUMPTIONS'!$B$6
A7: AI dev subscriptions × 24 mo | B7: 26400 | C7: =B7*'ASSUMPTIONS'!$B$6
A8: Security + SOC2 Type II | B8: 162000 | C8: =B8*'ASSUMPTIONS'!$B$6
A9: Legal + testing × 2 | B9: 90000 | C9: =B9*'ASSUMPTIONS'!$B$6
A10: TOTAL (incl. contingency) | B10: 4450298 | C10: =B10*'ASSUMPTIONS'!$B$6

Sheet PROVIDER MODEL
A1: Provider-only commercial model
A2: Illustrative gross-margin structure; validate with pricing pilots.
A4: Cost component | B4: Nature
A5: Infrastructure (Azure) | B5: Variable with claims volume
A6: AI runtime | B6: Variable per claim
A7: Security/compliance | B7: Fixed + annual
A8: Clearinghouse/integration | B8: Variable (per txn) — Stedi free tier for MVP
A9: Support | B9: Semi-fixed
A10: Gross margin | B10: Target 70–80% at scale (SaaS + usage)

Sheet PAYER MODEL
A1: Payer-only commercial model
A2: Illustrative gross-margin structure; validate with pricing pilots.
A4: Cost component | B4: Nature
A5: Infrastructure | B5: Fixed + variable
A6: Security/compliance | B6: Higher (payer trust, delegation)
A7: Integration | B7: Enterprise, per-payer
A8: AI runtime | B8: Variable
A9: Human oversight | B9: Required for regulated functions
A10: Gross margin | B10: Target 60–75% (enterprise, longer cycles)

Sheet COMBINED MODEL
A1: Combined provider + payer model
A2: Illustrative gross-margin structure; validate with pricing pilots.
A4: Cost component | B4: Nature
A5: Shared platform | B5: One codebase, amortized build
A6: Tenant isolation | B6: Adds engineering + possibly dedicated infra (enterprise)
A7: Integration | B7: Both sides
A8: Compliance | B8: Highest (both parties)
A9: Gross margin | B9: Blended 65–78%; strongest LTV via cross-side data network effects (governed)

Sheet BUILD BUY PARTNER
A1: Build / Buy / Partner
A3: Capability | B3: Decision | C3: Rationale
A4: Payer connectivity (EDI/API) | B4: BUY/PARTNER | C4: Clearinghouse (Stedi/Optum/Availity)
A5: Denial/appeal/estimation intelligence | B5: BUILD | C5: Proprietary value
A6: Payer Intelligence + Orchestration | B6: BUILD | C6: The moat
A7: AI voice | B7: BUY/INTEGRATE | C7: Voice provider under BAA
A8: Cloud/security primitives | B8: BUY | C8: Azure managed services
A9: Coverage criteria (InterQual/MCG) | B9: PARTNER/LICENSE | C9: License-gated
A10: Payer-side adjudication | B10: PARTNER/REGULATED | C10: Decision-support only; legal review

Sheet RISKS
A1: Risks
A3: Risk | B3: Mitigation
A4: Clearinghouse per-txn pricing opacity | B4: Capture Stedi cents; start on free tier; multi-vendor
A5: AI decision-limit regulation (CMS-4201-F, SB 1120) | B5: Human-in-the-loop; AI decision-support only
A6: PHI/security incident | B6: Zero Trust, encryption, private networking, SIEM, IR readiness
A7: Tenant data leakage | B7: RLS + app authz + isolation testing
A8: Payer onboarding delays | B8: Clearinghouse reach; portal/voice fallback
A9: AI cost overrun | B9: Model routing, caching, batch; per-claim budget guardrails
A10: Talent/timeline | B10: AI productivity uplift; realistic plan; contingency 15%
A11: Compliance cost | B11: Phase SOC2 → HITRUST; tooling automation

Sheet SECURITY CONTROLS
A1: Security controls
A3: Domain | B3: Controls
A4: Identity | B4: Entra ID, MFA, Conditional Access, PIM/JIT, Managed Identity
A5: Network | B5: Hub-spoke, Private Link/Endpoints, Firewall, WAF, DDoS, no public DB
A6: Data | B6: TLS 1.2+, AES-256 at rest, Key Vault/CMK, HSM (where justified), RLS
A7: AI | B7: AI Gateway: PHI detection → policy → redaction → approved model → validation → audit
A8: Monitoring | B8: Defender for Cloud, Sentinel SIEM, Monitor/App Insights, immutable audit
A9: SDLC | B9: SAST/DAST/SCA/secret/container/IaC scanning; protected main; PR review
A10: Governance | B10: Least privilege (humans + AI agents); high-risk actions human-approved

Sheet PHI DATA FLOW
A1: PHI data flow (AI Gateway)
A2: Dev uses synthetic/de-identified data only. Production PHI via approved services under BAA.
A4: Step | B4: Action
A5: 1 Ingress | B5: Authenticated request (Entra) over TLS
A6: 2 PHI detection | B6: Classify & detect PHI in payload
A7: 3 Policy engine | B7: Apply tenant + PHI policy; decide model + redaction
A8: 4 Redaction/tokenization | B8: Where appropriate before model call
A9: 5 Approved model | B9: Azure OpenAI (BAA) for PHI path; provider-agnostic gateway
A10: 6 Response validation | B10: Validate output; confidence scoring
A11: 7 Audit | B11: Immutable log: input refs, decision, model, confidence, approver

Sheet DR_BCP
A1: Disaster recovery & business continuity
A3: Tier | B3: RPO | C3: RTO | D3: Measures
A4: MVP | B4: ≤ 24h | C4: ≤ 8h | D4: Backups, PITR
A5: Production | B5: ≤ 1h | C5: ≤ 4h | D5: Geo-redundancy, failover, DR testing
A6: Enterprise | B6: ≤ 15m | C6: ≤ 1h | D6: Active-passive multi-region, ransomware recovery
A8: Continuity scenario | B8: Response
A9: AI provider outage | B9: Fallback: primary → secondary model → rules → human
A10: Clearinghouse/payer API outage | B10: Alternate channel; queue & retry; portal/voice
A11: Azure/DB outage | B11: Failover, restore from PITR/geo-backup
A12: Cyberattack/ransomware | B12: IR plan, isolation, immutable backups, restore

Sheet AI GOVERNANCE
A1: AI agent governance
A2: Agents are privileged software identities, not employees.
A4: Control | B4: Detail
A5: Agent identity | B5: Each agent has an identity + scoped permissions
A6: Permissions | B6: Tool / data / tenant / action — least privilege
A7: No unrestricted access | B7: No prod DB, prod deploy, or PHI without controls
A8: Human approval gates | B8: Prod deploy, DB/IAM/security/PHI changes, deletions, and any adjudication/medical-necessity/coverage/financial decision
A9: Audit | B9: Every agent action logged (input, decision, reason, confidence, channel, approver)

Sheet SOURCES
A1: Sources & evidence
A2: Prices are 2026 researched figures; verify live before board commitment. Quote-only items not invented.
A4: Item | B4: URL | C4: Confidence
A5: Anthropic Claude Max plan | B5: https://support.claude.com/en/articles/11049741-what-is-the-max-plan | C5: High
A6: Anthropic Claude Team plan | B6: https://support.claude.com/en/articles/9266767-what-is-the-team-plan | C6: High
A7: Anthropic Claude Enterprise billing | B7: https://support.claude.com/en/articles/11526368 | C7: Med-High
A8: Claude Code with Pro/Max | B8: https://support.claude.com/en/articles/11145838 | C8: High
A9: OpenAI ChatGPT Business pricing | B9: https://openai.com/business/pricing/ | C9: High
A10: OpenAI ChatGPT Enterprise (quote-only) | B10: https://openai.com/chatgpt/enterprise/ | C10: High
A11: Anthropic API pricing (secondary-corroborated) | B11: https://claude.com/pricing | C11: Med
A12: OpenAI API pricing | B12: https://openai.com/api/pricing/ | C12: Med
A13: Azure OpenAI Service pricing + HIPAA BAA | B13: https://azure.microsoft.com/en-us/pricing/details/cognitive-services/openai-service/ | C13: Med
A14: Azure OpenAI HIPAA eligibility (Microsoft Learn) | B14: https://learn.microsoft.com/en-us/azure/compliance/offerings/offering-hipaa-us | C14: High
A15: Azure AI Search pricing | B15: https://azure.microsoft.com/en-us/pricing/details/search/ | C15: Med
... A41: India developer salary benchmarks (Glassdoor/6figr/Levels) | B41: https://6figr.com/ | C41: Med
